neosmartblue/py/__init__.py
neosmartblue/py/const.py
neosmartblue/py/device.py
neosmartblue/py/generate_commands.py
neosmartblue/py/parse_status.py
neosmartblue/py/scan.py
neosmartblue_py-0.1.4.dist-info/LICENSE
neosmartblue_py-0.1.4.dist-info/METADATA
neosmartblue_py-0.1.4.dist-info/WHEEL
neosmartblue_py-0.1.4.dist-info/RECORD
