Metadata-Version: 2.3
Name: neosmartblue.py
Version: 0.1.4
Summary: A Python library for controlling Neo Smart Blinds via BlueLink Bluetooth connection
Keywords: bluetooth,ble,smart blinds,neo,home automation
Author: ikifar2012
Author-email: ikifar2012@users.noreply.github.com
Requires-Python: >=3.13,<3.14
Classifier: Development Status :: 3 - Alpha
Classifier: Intended Audience :: Developers
Classifier: License :: OSI Approved :: MIT License
Classifier: Operating System :: OS Independent
Classifier: Programming Language :: Python :: 3
Classifier: Programming Language :: Python :: 3.13
Classifier: Topic :: Home Automation
Classifier: Topic :: Software Development :: Libraries :: Python Modules
Requires-Dist: bleak (>=1.0.1)
Project-URL: Homepage, https://github.com/ikifar2012/neosmartblue.py
Project-URL: Issues, https://github.com/ikifar2012/neosmartblue.py/issues
Project-URL: Repository, https://github.com/ikifar2012/neosmartblue.py
